drf_annotations/__init__.py
drf_annotations/mixins.py
drf_annotations-0.0.5.dist-info/LICENSE.md
drf_annotations-0.0.5.dist-info/METADATA
drf_annotations-0.0.5.dist-info/WHEEL
drf_annotations-0.0.5.dist-info/top_level.txt
drf_annotations-0.0.5.dist-info/RECORD
